[{
  "_id": {
    "oid": "62369d0d5d4f7228e4d938da"
  },
  "checkout_timestamp": "03/11/22 17:36",
  "address": "3559 Chamblee Tucker Road  Atlanta GA 30341",
  "items": [
    "PRSL FZN FRT      XP    3.99 B",
    "PRSL FZN FRT      XP    4.99 B",
    "KRO CRM CHS             2.49 B",
    "SAS GRND BLCK PPR       1.29 B",
    "PRES FETA         <+    1.99 B",
    "KROGER BAKING CH  PC    2.00 B",
    "KROGER CHOCOLATE        3.99 B",
    "GRAPEFRUIT RED EST      9.45 B",
    "LEMON FANCY             3.99 B",
    "MANGOES                 5.00 B",
    "PRSL PARMESAN CHS       4.99 B",
    "MAC AND CHEESE    PC    4.99 B",
    "KRO ALLERGY TABLET      5.99 T",
    "TYFR SALAD KIT    PC    3.50 B",
    "KRO SALTED BUTTER PC    6.00 B",
    "WT      NECTARINES              2.51 B",
    "PILLSBURY FROSTINGPC    1.50 B",
    "PILLSBURY FROSTINGPC    1.50 B",
    "PRSL CHPTL PPR          2.49 B",
    "KRO SALT                0.59 B",
    "PILLSBURY BISCUITS      2.49 B",
    "KRO HVY CRM             2.29 B",
    "LA BNDTA TORTILLA       3.99 B",
    "KRO INST CHOC FDGE      0.65 B",
    "KRO INST CHOC FDGE      0.65 B",
    "KRO SHRED CHEESE  <+    4.99 B",
    "KROGER PIE CRUST        1.19 B",
    "KRUSTEAZ CAKE MIX PC    2.79 B",
    "KRUSTEAZ CAKE MIX PC    2.79 B",
    "SPK S SCAMPI      PC    5.99 B",
    "SPK S SCAMPI      PC    5.99 B",
    "OLE CHEESE              6.99 B",
    "KRO BACON               5.49 B",
    "SMFD LOIN FILLET  PC    5.99 B",
    "ARIZONA TEA             3.19 B",
    "KRO VITAMIN D MILK      2.99 B",
    "MXWLL HOUSE COFFEE<+    5.99 B",
    "MXWLL HOUSE COFFEE<+    5.99 B",
    "MMS MILK CHOCOLAT XP    8.99 B",
    "MISSION TORT CHIPS<+    1.49 B",
    "KROGER RICE             2.89 B",
    "SLMN ATLNTC LOIN       10.33 B",
    "AQSR SALMON       PC    7.99 B",
    "HTGF CHK BRST          10.31 B",
    "HTGF CHK DRMST          7.86 B",
    "SLAB RIBS              12.99 B",
    "BIG K COLA 12PK   PC    2.15 B",
    "SARALEE ARTI ROLLSPC    3.00 B",
    "KROGER EGGS             2.38 B",
    "BKRY DONUT              4.14 B"
  ],
  "sales": [
    {
      "item_index": 4,
      "sale_code": "SC      KROGER SAVINGS    1.00"
    },
    {
      "item_index": 4,
      "sale_code": "SC      Mega Event Savings1.00"
    },
    {
      "item_index": 5,
      "sale_code": "SC      KROGER SAVINGS    0.79"
    },
    {
      "item_index": 11,
      "sale_code": "SC      KROGER SAVINGS    1.00"
    },
    {
      "item_index": 13,
      "sale_code": "SC      KROGER SAVINGS    0.69"
    },
    {
      "item_index": 14,
      "sale_code": "SC      KROGER SAVINGS    0.49"
    },
    {
      "item_index": 16,
      "sale_code": "SC      KROGER SAVINGS    0.39"
    },
    {
      "item_index": 16,
      "sale_code": "SC      KROGER SAVINGS    0.39"
    },
    {
      "item_index": 25,
      "sale_code": "SC      KROGER SAVINGS    1.00"
    },
    {
      "item_index": 25,
      "sale_code": "SC      Mega Event Savings1.00"
    },
    {
      "item_index": 27,
      "sale_code": "SC      KROGER SAVINGS    1.50"
    },
    {
      "item_index": 27,
      "sale_code": "SC      KROGER SAVINGS    1.50"
    },
    {
      "item_index": 29,
      "sale_code": "SC      KROGER SAVINGS    2.50"
    },
    {
      "item_index": 29,
      "sale_code": "SC      KROGER SAVINGS    2.50"
    },
    {
      "item_index": 33,
      "sale_code": "SC      KROGER SAVINGS    3.00"
    },
    {
      "item_index": 36,
      "sale_code": "SC      Mega Event Savings1.00"
    },
    {
      "item_index": 36,
      "sale_code": "SC      Mega Event Savings1.00"
    },
    {
      "item_index": 38,
      "sale_code": "SC      KROGER SAVINGS    4.50"
    },
    {
      "item_index": 39,
      "sale_code": "SC      KROGER SAVINGS    0.80"
    },
    {
      "item_index": 39,
      "sale_code": "SC      Mega Event Savings1.00"
    },
    {
      "item_index": 42,
      "sale_code": "SC      KROGER SAVINGS    2.00"
    },
    {
      "item_index": 46,
      "sale_code": "SC      KROGER SAVINGS    0.24"
    },
    {
      "item_index": 46,
      "sale_code": "SC      eCpn KRO BKZro Sug0.60"
    },
    {
      "item_index": 47,
      "sale_code": "SC      KROGER SAVINGS    1.29"
    },
    {
      "item_index": 49,
      "sale_code": "SC      Fuel Points"
    }
  ],
  "cashier": "CHEC 520",
  "payment_type": "CHASE VISA Purchase",
  "fuel_points_earned": "218",
  "fuel_points_month": "251",
  "last_month_fuel_points": "384"
}]